mnetwork/__about__.py
mnetwork/__init__.py
mnetwork/main.py
mnetwork-1.0.0.dist-info/METADATA
mnetwork-1.0.0.dist-info/WHEEL
mnetwork-1.0.0.dist-info/entry_points.txt
mnetwork-1.0.0.dist-info/licenses/LICENSE
mnetwork-1.0.0.dist-info/RECORD
